pagtest/__init__.py
pagtest/print1.py
pagtest/print2.py
pagtest-1.0.0.dist-info/METADATA
pagtest-1.0.0.dist-info/WHEEL
pagtest-1.0.0.dist-info/top_level.txt
pagtest-1.0.0.dist-info/RECORD
